amdgpu_pptable/__init__.py
amdgpu_pptable/dump.py
amdgpu_pptable/pptable_v1_0.py
amdgpu_pptable/smu_v11_0_pptable_navi10.py
amdgpu_pptable/vega10_pptable.py
amdgpu_pptable/version.py
amdgpu_pptable/version_detect.py
amdgpu_pptable/generated/__init__.py
amdgpu_pptable/generated/pptable_v1_0.py
amdgpu_pptable/generated/smu_v11_0_pptable_navi10.py
amdgpu_pptable/generated/vega10_pptable.py
amdgpu_pptable-0.9.2.dist-info/LICENSE.txt
amdgpu_pptable-0.9.2.dist-info/METADATA
amdgpu_pptable-0.9.2.dist-info/WHEEL
amdgpu_pptable-0.9.2.dist-info/top_level.txt
amdgpu_pptable-0.9.2.dist-info/RECORD
