Metadata-Version: 2.1
Name: amdgpu-pptable
Version: 0.9.2
Summary: AMDGPU PowerPlay table parser
Home-page: https://github.com/amezin/amdgpu-pptable
Author: Aleksandr Mezin
Author-email: mezin.alexander@gmail.com
License: UNKNOWN
Keywords: amdgpu radeon powerplay
Platform: UNKNOWN
Classifier: License :: OSI Approved :: MIT License
Classifier: Programming Language :: Python :: 3
Classifier: Programming Language :: Python :: 3.6
Classifier: Programming Language :: Python :: 3.7
Classifier: Programming Language :: Python :: 3.8
Classifier: Development Status :: 4 - Beta
Classifier: Intended Audience :: Developers
Classifier: Topic :: Software Development :: Libraries
Classifier: Topic :: System :: Hardware
Requires-Python: >=3.6
